{
  "name": "cronapp-lib-js",
  "version": "2.0.0",
  "homepage": "https://github.com/CronApp/cronapp-lib-js",
  "authors": [
    "Techne Engenharia e Sistemas <contato@techne.com.br>"
  ],
  "description": "Javascript library for CronApp's projects",
  "main": "cronapp.lib.js",
  "license": "MIT",
  "ignore": [
    "**/.*",
    "node_modules",
    "bower_components",
    "test",
    "tests"
  ],
  "_release": "2.0.0",
  "_resolution": {
    "type": "version",
    "tag": "2.0.0",
    "commit": "0a427cd50f1210257d901b244d749f49f5a94967"
  },
  "_source": "https://github.com/CronApp/cronapp-lib-js.git",
  "_target": "2.0.0",
  "_originalSource": "cronapp-lib-js"
}